neco_m3u8/decrypto.py
neco_m3u8/ffmpeg.py
neco_m3u8/neco_m3u8.py
neco_m3u8-0.0.4.dist-info/METADATA
neco_m3u8-0.0.4.dist-info/WHEEL
neco_m3u8-0.0.4.dist-info/top_level.txt
neco_m3u8-0.0.4.dist-info/RECORD
